{
  "Version": "2012-10-17",
  "Statement": [
    {
      "Sid": "Stmt1540815682194",
      "Action": [
        "ecr:BatchCheckLayerAvailability",
        "ecr:BatchGetImage",
        "ecr:CompleteLayerUpload",
        "ecr:CreateRepository",
        "ecr:DescribeImages",
        "ecr:DescribeRepositories",
        "ecr:GetAuthorizationToken",
        "ecr:GetDownloadUrlForLayer",
        "ecr:GetRepositoryPolicy",
        "ecr:InitiateLayerUpload",
        "ecr:ListImages",
        "ecr:PutImage",
        "ecr:SetRepositoryPolicy",
        "ecr:UploadLayerPart"
      ],
      "Effect": "Allow",
      "Resource": "*"
    }
  ]
}